{
  "_format": "ethers-rs-sol-cache-3",
  "files": {
    "/Users/cleanunicorn/Development/github.com/cleanunicorn/4byte-update/contracts/Test4Byte copy.sol": {
      "lastModificationDate": 1649856892054,
      "contentHash": "aa51bafe4a3badb0be0cfe9bfa46511f",
      "sourceName": "contracts/Test4Byte copy.sol",
      "solcConfig": {
        "settings": {
          "optimizer": {
            "enabled": true,
            "runs": 200
          },
          "outputSelection": {
            "*": {
              "": [
                "ast"
              ],
              "*": [
                "abi",
                "evm.bytecode",
                "evm.deployedBytecode",
                "evm.methodIdentifiers"
              ]
            }
          },
          "evmVersion": "london"
        }
      },
      "imports": [],
      "versionRequirement": null,
      "artifacts": {
        "WeirdContract": {
          "0.8.13+commit.abaa5c0e.Darwin.appleclang": "Test4Byte copy.sol/WeirdContract.json"
        }
      }
    },
    "/Users/cleanunicorn/Development/github.com/cleanunicorn/4byte-update/contracts/Test4Byte.sol": {
      "lastModificationDate": 1649856892054,
      "contentHash": "aa51bafe4a3badb0be0cfe9bfa46511f",
      "sourceName": "contracts/Test4Byte.sol",
      "solcConfig": {
        "settings": {
          "optimizer": {
            "enabled": true,
            "runs": 200
          },
          "outputSelection": {
            "*": {
              "": [
                "ast"
              ],
              "*": [
                "abi",
                "evm.bytecode",
                "evm.deployedBytecode",
                "evm.methodIdentifiers"
              ]
            }
          },
          "evmVersion": "london"
        }
      },
      "imports": [],
      "versionRequirement": null,
      "artifacts": {
        "WeirdContract": {
          "0.8.13+commit.abaa5c0e.Darwin.appleclang": "Test4Byte.sol/WeirdContract.json"
        }
      }
    }
  }
}